django_celery_beat_rrule/__init__.py
django_celery_beat_rrule/apps.py
django_celery_beat_rrule/model_entry.py
django_celery_beat_rrule/models.py
django_celery_beat_rrule/rrule_serializer.py
django_celery_beat_rrule/rruleschedule.py
django_celery_beat_rrule/schedulers.py
django_celery_beat_rrule/signals.py
django_celery_beat_rrule/migrations/0001_initial.py
django_celery_beat_rrule/migrations/__init__.py
django_celery_beat_rrule-0.0.3.dist-info/LICENSE
django_celery_beat_rrule-0.0.3.dist-info/METADATA
django_celery_beat_rrule-0.0.3.dist-info/WHEEL
django_celery_beat_rrule-0.0.3.dist-info/top_level.txt
django_celery_beat_rrule-0.0.3.dist-info/RECORD
