Metadata-Version: 2.2
Name: django-celery-beat-rrule
Version: 0.0.3
Summary: Add a RruleDatabaseScheduler, automatically execute tasks based on custom rrule schedules
Author-email: Vlad Tabakov <contact@vladtabakov.com>
License: The BSD 3-Clause License The following is a BSD 3-Clause ("BSD New" or "BSD Simplified") license template. To generate your own license, change the values of OWNER, ORGANIZATION and YEAR from their original values as given here, and substitute your own.
Project-URL: Homepage, https://github.com/Wattabak/django-celery-beat-rrule
Keywords: django-celery-beat,rrule,dateutil
Classifier: License :: OSI Approved :: BSD License
Classifier: Programming Language :: Python
Classifier: Programming Language :: Python :: 3
Requires-Python: >=3.7
License-File: LICENSE
Requires-Dist: dateutils>=0.6.12
Requires-Dist: django-celery-beat>=2.0.0
Provides-Extra: dev
Requires-Dist: black; extra == "dev"
Requires-Dist: tox; extra == "dev"
Requires-Dist: isort; extra == "dev"
Requires-Dist: pytest; extra == "dev"
